Fixed_Priority_Arbiter.v
/*
*********************************** Fixed Priority Arbiter *************************************

Assume the priority order is : REQ[3] > REG[2] > REQ[1] > REQ[0]
*/

module Fixed_Priority_Arbiter(

        input            clk,
	input            reset_n,
        input [3:0]      i_Req,
        output reg [3:0] o_Gnt
);

  always @ (posedge clk or negedge reset_n)
	begin		
          if(!reset_n)
				o_Gnt <= 4'b0000;
          else if(i_Req[3])
				o_Gnt <= 4'b1000;
          else if(i_Req[2])
				o_Gnt <= 4'b0100;
          else if(i_Req[1])
				o_Gnt <= 4'b0010;
          else if(i_Req[0])
				o_Gnt <= 4'b0001;
          else
				o_Gnt <= 4'b0000;
	end
endmodule  

// Fixed_Priority_Arbiter

Fixed_Priority_Arbiter_tb.v
/************************************ Fixed Priority Arbiter *************************************

Assume the priority order is : REQ[3] > REG[2] > REQ[1] > REQ[0]
*/

// Code your design here


module Fixed_Priority_Arbiter_TB;
  
  reg          clk;
  reg          reset_n;
  reg [3:0]    i_Req;
  wire [3:0]   o_Gnt;
  
  //Instantiate Design Under Test
  
  Fixed_Priority_Arbiter DUT(
     
    .clk                 (clk), 
    .reset_n             (reset_n), 
    .i_Req               (i_Req), 
    .o_Gnt               (o_Gnt)
  );
  
  //Generate a 10 ns  Time Period Clock 
  always #5 clk = ~clk;
  
  //Drive the DUT or Generate stimuli for the DUT
  
  initial begin
    clk = 0;
    reset_n = 0;
    i_Req = 4'b0;
    // Assert the Asynchronous Reset after 1 clock period 
    //#10 rst_n = 0;
    //Deassert the Reset
    #5 reset_n = 1;
    
    @(negedge clk) i_Req = 4'b1000;    
    
    @(negedge clk) i_Req = 4'b1010;
    
    @(negedge clk) i_Req = 4'b0010;
    
    @(negedge clk) i_Req = 4'b0110;
    
    @(negedge clk) i_Req = 4'b1110;
    
    @(negedge clk) i_Req = 4'b1111;
    
    @(negedge clk) i_Req = 4'b0100;
    
    @(negedge clk) i_Req = 4'b0010;
    
    #5 reset_n = 0;    
    #100 $finish;
  end  
   initial begin
    // below two lines are used to show waveform
    $dumpfile("dump.vcd");
    $dumpvars();
  end  
endmodule

dump.vcd
$date
	Sat Dec 13 13:52:50 2025
$end
$version
	Icarus Verilog
$end
$timescale
	1s
$end
$scope module Fixed_Priority_Arbiter_TB $end
$var wire 4 ! o_Gnt [3:0] $end
$var reg 1 " clk $end
$var reg 4 # i_Req [3:0] $end
$var reg 1 $ reset_n $end
$scope module DUT $end
$var wire 1 " clk $end
$var wire 4 % i_Req [3:0] $end
$var wire 1 $ reset_n $end
$var reg 4 & o_Gnt [3:0] $end
$upscope $end
$upscope $end
$enddefinitions $end
$comment Show the parameter values. $end
$dumpall
$end
#0
$dumpvars
b0 &
b0 %
0$
b0 #
0"
b0 !
$end
#5
1$
1"
#10
b1000 #
b1000 %
0"
#15
b1000 !
b1000 &
1"
#20
b1010 #
b1010 %
0"
#25
1"
#30
b10 #
b10 %
0"
#35
b10 !
b10 &
1"
#40
b110 #
b110 %
0"
#45
b100 !
b100 &
1"
#50
b1110 #
b1110 %
0"
#55
b1000 !
b1000 &
1"
#60
b1111 #
b1111 %
0"
#65
1"
#70
b100 #
b100 %
0"
#75
b100 !
b100 &
1"
#80
b10 #
b10 %
0"
#85
b0 !
b0 &
0$
1"
